docker_software_manager-0.2.1.data/scripts/dsm
docker_software_manager-0.2.1.dist-info/RECORD
docker_software_manager-0.2.1.dist-info/METADATA
docker_software_manager-0.2.1.dist-info/entry_points.txt
docker_software_manager-0.2.1.dist-info/pydist.json
docker_software_manager-0.2.1.dist-info/WHEEL
docker_software_manager-0.2.1.dist-info/top_level.txt
docker_software_manager-0.2.1.dist-info/DESCRIPTION.rst
dsm/cli.py
dsm/__init__.py
dsm/defaults.conf
dsm/docker-gen/update.sh
dsm/docker-gen/remove.sh
dsm/docker-gen/install.sh
dsm/docker-gen/docker-gen-nginx.service
dsm/docker-gen/nginx.tmpl
dsm/software-template/docker-compose.yml
dsm/software-template/software.service
dsm/software-template/backups/.placeholder
dsm/software-template/data/.placeholder
