Metadata-Version: 2.0
Name: docker-software-manager
Version: 0.2.1
Summary: Manage your server software with a combination of docker, systemd, docker-compose, docker-gen and nginx 
Home-page: https://github.com/robomod/docker-software-manager
Author: Andreas Ihrig (RoboMod)
Author-email: mod.andy@gmx.de
License: GPLv2
Platform: UNKNOWN
Requires-Dist: docker-compose
